django_rundirect/__init__.py
django_rundirect/management/__init__.py
django_rundirect/management/commands/__init__.py
django_rundirect/management/commands/rundirect.py
django_rundirect/management/commands/runline.py
django_rundirect-0.3.0.dist-info/DESCRIPTION.rst
django_rundirect-0.3.0.dist-info/METADATA
django_rundirect-0.3.0.dist-info/RECORD
django_rundirect-0.3.0.dist-info/WHEEL
django_rundirect-0.3.0.dist-info/metadata.json
django_rundirect-0.3.0.dist-info/top_level.txt
