Metadata-Version: 2.0
Name: django-rundirect
Version: 0.3.0
Summary: UNKNOWN
Home-page: https://github.com/socrateslee/django_rundirect
Author: Lichun
Author-email: UNKNOWN
License: MIT
Platform: UNKNOWN
Classifier: Environment :: Console
Classifier: Framework :: Django
Classifier: Intended Audience :: Developers
Classifier: License :: OSI Approved :: MIT License
Classifier: Programming Language :: Python
Requires-Dist: django
